fastrun/__init__.py
fastrun/__main__.py
fastrun/android/__init__.py
fastrun/android/handle.py
fastrun/android/script.py
fastrun/common/__init__.py
fastrun/common/cli.py
fastrun/common/command.py
fastrun/common/custom.py
fastrun/common/process.py
fastrun/common/scaffold.py
fastrun-1.0.4.dist-info/LICENSE
fastrun-1.0.4.dist-info/METADATA
fastrun-1.0.4.dist-info/WHEEL
fastrun-1.0.4.dist-info/top_level.txt
fastrun-1.0.4.dist-info/RECORD
