Metadata-Version: 2.1
Name: fastrun
Version: 1.0.4
Summary: 快速启动-android稳定性测试
Home-page: https://gitee.com/dongfang_rising_test/test-tool.git
Author: liFeng
Author-email: 960158047@qq.com
License: UNKNOWN
Platform: UNKNOWN
Classifier: Programming Language :: Python :: 3
Classifier: License :: OSI Approved :: MIT License
Classifier: Operating System :: OS Independent
Requires-Python: >=3.7
License-File: LICENSE
Requires-Dist: Jinja2 (==3.0.3)
Requires-Dist: pyyaml (==5.4.1)
